screenplay_pdf_to_json/__init__.py
screenplay_pdf_to_json/screenplay_pdf_to_json.py
screenplay_to_json_openai-1.0.3.dist-info/LICENSE
screenplay_to_json_openai-1.0.3.dist-info/METADATA
screenplay_to_json_openai-1.0.3.dist-info/WHEEL
screenplay_to_json_openai-1.0.3.dist-info/top_level.txt
screenplay_to_json_openai-1.0.3.dist-info/RECORD
