Metadata-Version: 2.1
Name: screenplay-to-json-openai
Version: 1.0.3
Summary: A tool to a screenplay PDF to JSON format using OpenAI Vision Transformer Analysis.
Author: Alexis Kirke
Author-email: alexiskirke2@gmail.com
Classifier: Programming Language :: Python :: 3
Classifier: License :: OSI Approved :: MIT License
Classifier: Operating System :: OS Independent
Requires-Python: >=3.6
License-File: LICENSE
Requires-Dist: openai
Requires-Dist: pdf2image
Requires-Dist: Pillow
